{"nodes": [{"id": "c_users_user_onedrive_desktop_tidl_main_tidl_main_src_hooks_use_prx_encounter_status_ts", "label": "use-prx-encounter-status.ts", "file_type": "code", "source_file": "C:\\Users\\User\\OneDrive\\Desktop\\tidl-main\\tidl-main\\src\\hooks\\use-prx-encounter-status.ts", "source_location": "L1"}, {"id": "hooks_use_prx_encounter_status_state", "label": "State", "file_type": "code", "source_file": "C:\\Users\\User\\OneDrive\\Desktop\\tidl-main\\tidl-main\\src\\hooks\\use-prx-encounter-status.ts", "source_location": "L4"}, {"id": "hooks_use_prx_encounter_status_useprxencounterstatus", "label": "usePrxEncounterStatus()", "file_type": "code", "source_file": "C:\\Users\\User\\OneDrive\\Desktop\\tidl-main\\tidl-main\\src\\hooks\\use-prx-encounter-status.ts", "source_location": "L15"}], "edges": [{"source": "c_users_user_onedrive_desktop_tidl_main_tidl_main_src_hooks_use_prx_encounter_status_ts", "target": "react", "relation": "imports_from", "context": "import", "confidence": "EXTRACTED", "source_file": "C:\\Users\\User\\OneDrive\\Desktop\\tidl-main\\tidl-main\\src\\hooks\\use-prx-encounter-status.ts", "source_location": "L1", "weight": 1.0}, {"source": "c_users_user_onedrive_desktop_tidl_main_tidl_main_src_hooks_use_prx_encounter_status_ts", "target": "c_users_user_onedrive_desktop_tidl_main_tidl_main_src_lib_prescribe_rx_index_ts", "relation": "imports_from", "context": "import", "confidence": "EXTRACTED", "source_file": "C:\\Users\\User\\OneDrive\\Desktop\\tidl-main\\tidl-main\\src\\hooks\\use-prx-encounter-status.ts", "source_location": "L2", "weight": 1.0}, {"source": "c_users_user_onedrive_desktop_tidl_main_tidl_main_src_hooks_use_prx_encounter_status_ts", "target": "prescribe_rx_index_fetchprxencounter", "relation": "imports", "context": "import", "confidence": "EXTRACTED", "source_file": "C:\\Users\\User\\OneDrive\\Desktop\\tidl-main\\tidl-main\\src\\hooks\\use-prx-encounter-status.ts", "source_location": "L2", "weight": 1.0}, {"source": "c_users_user_onedrive_desktop_tidl_main_tidl_main_src_hooks_use_prx_encounter_status_ts", "target": "prescribe_rx_index_prxencounter", "relation": "imports", "context": "import", "confidence": "EXTRACTED", "source_file": "C:\\Users\\User\\OneDrive\\Desktop\\tidl-main\\tidl-main\\src\\hooks\\use-prx-encounter-status.ts", "source_location": "L2", "weight": 1.0}, {"source": "c_users_user_onedrive_desktop_tidl_main_tidl_main_src_hooks_use_prx_encounter_status_ts", "target": "hooks_use_prx_encounter_status_state", "relation": "contains", "confidence": "EXTRACTED", "source_file": "C:\\Users\\User\\OneDrive\\Desktop\\tidl-main\\tidl-main\\src\\hooks\\use-prx-encounter-status.ts", "source_location": "L4", "weight": 1.0}, {"source": "c_users_user_onedrive_desktop_tidl_main_tidl_main_src_hooks_use_prx_encounter_status_ts", "target": "hooks_use_prx_encounter_status_useprxencounterstatus", "relation": "contains", "confidence": "EXTRACTED", "source_file": "C:\\Users\\User\\OneDrive\\Desktop\\tidl-main\\tidl-main\\src\\hooks\\use-prx-encounter-status.ts", "source_location": "L15", "weight": 1.0}], "raw_calls": [{"caller_nid": "hooks_use_prx_encounter_status_useprxencounterstatus", "callee": "useState", "is_member_call": false, "source_file": "C:\\Users\\User\\OneDrive\\Desktop\\tidl-main\\tidl-main\\src\\hooks\\use-prx-encounter-status.ts", "source_location": "L19"}, {"caller_nid": "hooks_use_prx_encounter_status_useprxencounterstatus", "callee": "useRef", "is_member_call": false, "source_file": "C:\\Users\\User\\OneDrive\\Desktop\\tidl-main\\tidl-main\\src\\hooks\\use-prx-encounter-status.ts", "source_location": "L20"}, {"caller_nid": "hooks_use_prx_encounter_status_useprxencounterstatus", "callee": "useEffect", "is_member_call": false, "source_file": "C:\\Users\\User\\OneDrive\\Desktop\\tidl-main\\tidl-main\\src\\hooks\\use-prx-encounter-status.ts", "source_location": "L22"}]}